{
  "briefs": [
    {
      "id": 1,
      "title": "Round box for wine",
      "comment": "I need 1000 round boxes",
      "productId": 3
    },
    {
      "id": 2,
      "title": "Beautiful bag Box",
      "comment": "Beautiful bag Box with a cord",
      "productId": 1
    },
    {
      "id": 3,
      "title": "03",
      "comment": "erherherherherhre",
      "productId": 2
    },
    {
      "id": 4,
      "title": "the title04",
      "comment": "bfnbjytrkldse",
      "productId": 4
    },
    {
      "id": 5,
      "title": "06",
      "comment": "fzegzgzgz",
      "productId": 1
    },
    {
      "id": 6,
      "title": "the title",
      "comment": "fnhsrtjy kk  d",
      "productId": 2
    }
  ],
  "products": [
    {
      "id": 1,
      "name": "Bag Box"
    },
    {
      "id": 2,
      "name": "Oval Box"
    },
    {
      "id": 3,
      "name": "Round Box"
    },
    {
      "id": 4,
      "name": "Other Box"
    }
  ]
}